{"basketball": {"1964": {"ranked_players": ["United States", "Soviet Union", "SFR Yugoslavia", "Puerto Rico", "Brazil", "Italy", "Uruguay", "Poland", "Mexico", "Japan", "Finland", "Australia", "Peru", "Hungary", "South Korea", "Canada"]}, "1968": {"ranked_players": ["Soviet Union", "United States", "SFR Yugoslavia", "Brazil", "Italy", "Mexico", "Spain", "Poland", "Puerto Rico", "Bulgaria", "Panama", "Cuba", "Philippines", "South Korea", "Senegal", "Morocco"]}, "1972": {"ranked_players": ["Soviet Union", "United States", "Cuba", "Puerto Rico", "Italy", "Brazil", "Czechoslovakia", "Australia", "Spain", "West Germany", "Poland", "Philippines", "Japan", "Egypt", "Senegal", "Yugoslavia", "SFR Yugoslavia"]}, "1976": {"ranked_players": ["Soviet Union", "United States", "Canada", "Czechoslovakia", "Japan", "Yugoslavia", "Cuba", "Bulgaria", "Italy", "Australia", "Mexico", "Puerto Rico", "Egypt"]}, "1980": {"ranked_players": ["Soviet Union", "Yugoslavia", "Italy", "Cuba", "Spain", "Australia", "Brazil", "Poland", "Czechoslovakia", "Sweden", "Senegal", "India", "Bulgaria", "Hungary"]}, "1984": {"ranked_players": ["United States", "Canada", "China", "Yugoslavia", "Australia", "South Korea", "Spain", "Italy", "Uruguay", "West Germany", "Brazil", "France", "Egypt"]}, "2000": {"ranked_players": ["United States", "Lithuania", "Australia", "France", "Canada", "FR Yugoslavia", "Italy", "Russia", "Spain", "China", "New Zealand", "Angola"]}, "2004": {"ranked_players": ["Spain", "Greece", "China", "New Zealand", "Australia", "United States", "Czech Republic", "Puerto Rico", "Serbia and Montenegro", "Japan", "Nigeria", "South Korea", "Angola", "Lithuania", "Russia", "Brazil", "Argentina", "Italy"]}, "2008": {"ranked_players": ["United States", "Spain", "Argentina", "Lithuania", "Australia", "Greece", "Croatia", "China", "Russia", "Germany", "Iran", "Angola"]}, "2012": {"ranked_players": ["United States", "Russia", "Spain", "Argentina", "Brazil", "France", "Australia", "Lithuania", "Great Britain", "Nigeria", "Tunisia", "China"]}, "2016": {"ranked_players": ["United States", "Spain", "Australia", "Serbia", "Argentina", "France", "Croatia", "Lithuania", "Brazil", "Nigeria", "Venezuela", "China"]}, "2020": {"ranked_players": ["United States", "Australia", "France", "Slovenia", "Spain", "Italy", "Argentina", "Germany", "Czech Republic", "Japan", "Nigeria", "Iran"]}}, "cricket": {"1975": {"ranked_players": ["West Indies", "Australia", "England", "New Zealand", "Pakistan", "India", "Sri Lanka", "East Africa"]}, "1979": {"ranked_players": ["England", "West Indies", "New Zealand", "Pakistan", "Sri Lanka", "Australia", "India", "Canada", "Match abandoned"]}, "1983": {"ranked_players": ["India", "West Indies", "England", "Pakistan", "New Zealand", "Australia", "Zimbabwe", "Sri Lanka"]}, "1987": {"ranked_players": ["Australia", "England", "India", "Pakistan", "West Indies", "New Zealand", "Sri Lanka", "Zimbabwe"]}, "1992": {"ranked_players": ["England", "Pakistan", "New Zealand", "South Africa", "West Indies", "Australia", "Sri Lanka", "India", "Zimbabwe", "No result"]}, "1996": {"ranked_players": ["Sri Lanka", "Australia", "India", "West Indies", "South Africa", "Pakistan", "New Zealand", "England", "Kenya", "Zimbabwe", "Netherlands", "United Arab Emirates", "United Arab"]}, "1999": {"ranked_players": ["Australia", "Pakistan", "South Africa", "New Zealand", "India", "Zimbabwe", "West Indies", "England", "Bangladesh", "Sri Lanka", "Scotland", "Kenya", "No result", "Match tied"]}, "2003": {"ranked_players": ["Australia", "India", "Kenya", "Sri Lanka", "New Zealand", "Zimbabwe", "West Indies", "South Africa", "England", "Pakistan", "Canada", "Netherlands", "Bangladesh", "Namibia", "No result", "Match tied"]}, "2007": {"ranked_players": ["Sri Lanka", "Ireland", "Australia", "England", "New Zealand", "West Indies", "Bangladesh", "South Africa", "India", "177", "209", "Pakistan", "Scotland", "Zimbabwe", "Kenya", "Bermuda", "221", "300", "348", "230", "77", "154", "226", "243", "193", "91", "219", "143", "356", "263", "247", "251", "235", "152", "174", "303", "104", "266", "322", "183", "349", "202", "132", "241", "363", "331", "279", "199", "Canada", "94/", "254", "318", "413", "191", "321", "377", "136", "186", "358", "353", "334", "Netherlands"]}, "2011": {"ranked_players": ["India", "Sri Lanka", "Pakistan", "New Zealand", "South Africa", "England", "Australia", "West Indies", "Bangladesh", "Ireland", "Zimbabwe", "Netherlands", "Canada", "Kenya"]}, "2015": {"ranked_players": ["New Zealand", "Australia", "India", "South Africa", "Pakistan", "Sri Lanka", "Bangladesh", "West Indies", "Ireland", "Afghanistan", "Zimbabwe", "England", "United Arab Emirates", "Scotland"]}, "2019": {"ranked_players": ["England", "New Zealand", "Australia", "India", "Pakistan", "South Africa", "Sri Lanka", "Bangladesh", "West Indies", "Afghanistan", "Match abandoned", "No result", "Match &"]}}, "field_hockey": {"1971": {"ranked_players": ["West Germany", "Kenya", "India", "Pakistan", "Spain", "France", "Netherlands", "Australia", "Japan", "Argentina"]}, "1973": {"ranked_players": ["Netherlands", "West Germany", "Spain", "India", "Pakistan", "Argentina", "New Zealand", "England", "Malaysia", "Belgium", "Japan", "Kenya"]}, "1975": {"ranked_players": ["India", "Australia", "Pakistan", "West Germany", "England", "Netherlands", "Argentina", "New Zealand", "Malaysia", "Poland", "Spain", "Ghana"]}, "1978": {"ranked_players": ["Pakistan", "Australia", "Argentina", "Malaysia", "Ireland", "Spain", "Netherlands", "West Germany", "Poland", "India", "England", "Canada", "Italy", "Belgium"]}, "1982": {"ranked_players": ["Pakistan", "Australia", "India", "West Germany", "Netherlands", "England", "New Zealand", "Spain", "Poland", "Soviet Union", "Malaysia", "Argentina"]}, "1986": {"ranked_players": ["Australia", "England", "Netherlands", "Spain", "Soviet Union", "West Germany", "Poland", "New Zealand", "Argentina", "Pakistan", "India", "Canada"]}, "1994": {"ranked_players": ["Pakistan", "Netherlands", "Australia", "Argentina", "England", "Spain", "India", "Germany", "South Africa", "South Korea", "Belgium", "Belarus"]}, "1998": {"ranked_players": ["Netherlands", "Spain", "Germany", "Pakistan", "Australia", "England", "India", "South Korea", "New Zealand", "Canada", "Malaysia", "Poland"]}, "2002": {"ranked_players": ["Australia", "Germany", "Netherlands", "Pakistan", "Argentina", "South Korea", "England", "Spain", "Malaysia", "New Zealand", "India", "Japan", "South Africa", "Poland", "Belgium", "Cuba"]}, "2006": {"ranked_players": ["Germany", "Australia", "Spain", "Netherlands", "England", "South Korea", "Japan", "Pakistan", "New Zealand", "Argentina", "India", "South Africa"]}, "2010": {"ranked_players": ["Australia", "Germany", "Netherlands", "England", "Spain", "South Korea", "Argentina", "New Zealand", "South Africa", "India", "Pakistan", "Canada"]}, "2018": {"ranked_players": ["Belgium", "Netherlands", "England", "Australia", "France", "Germany", "India", "Argentina", "New Zealand", "China", "Canada", "Pakistan", "Spain", "Malaysia", "Ireland", "South Africa"]}, "2023": {"ranked_players": ["Germany", "Netherlands", "Belgium", "India", "Argentina", "Australia", "Malaysia", "France", "Spain", "New Zealand", "South Korea", "South Africa", "Wales", "Chile", "Japan", "England"]}}, "futsal": {"1989": {"ranked_players": ["United States", "Brazil", "Belgium", "Netherlands", "Italy", "Hungary", "Paraguay", "Argentina", "Spain", "Denmark", "Australia", "Canada", "Algeria", "Saudi Arabia", "Zimbabwe", "Japan"]}, "1992": {"ranked_players": ["Brazil", "Spain", "Iran", "United States", "Netherlands", "Belgium", "Argentina", "Poland", "Russia", "Italy", "Paraguay", "Australia", "Hong Kong", "Costa Rica", "China", "Nigeria"]}, "1996": {"ranked_players": ["Brazil", "Spain", "Russia", "Ukraine", "Italy", "Uruguay", "Netherlands", "Belgium", "Argentina", "Egypt", "Iran", "United States", "Cuba", "Malaysia", "Australia", "China"]}, "2000": {"ranked_players": ["Russia", "Spain", "Portugal", "Brazil", "Netherlands", "Egypt", "Croatia", "Argentina", "Guatemala", "Uruguay", "Costa Rica", "Iran", "Australia", "Cuba", "Kazakhstan", "Thailand"]}, "2004": {"ranked_players": ["Spain", "Brazil", "Italy", "Argentina", "Ukraine", "Portugal", "Czech Republic", "United States", "Egypt", "Thailand", "Paraguay", "Iran", "Australia", "Cuba", "Chinese Taipei", "Japan"]}, "2008": {"ranked_players": ["Brazil", "Spain", "Italy", "Russia", "Iran", "Paraguay", "Argentina", "Ukraine", "Portugal", "Japan", "Guatemala", "Czech Republic", "Cuba", "Thailand", "Egypt", "Solomon Islands", "Libya", "United States", "Uruguay", "China"]}, "2012": {"ranked_players": ["Brazil", "Italy", "Spain", "Colombia", "Russia", "Ukraine", "Argentina", "Portugal", "Serbia", "Iran", "Japan", "Paraguay", "Czech Republic", "Panama", "Egypt", "Thailand", "Guatemala", "Kuwait", "Costa Rica", "Solomon Islands", "Australia", "Morocco", "Mexico", "Libya"]}, "2016": {"ranked_players": ["Argentina", "Russia", "Portugal", "Iran", "Spain", "Paraguay", "Azerbaijan", "Egypt", "Brazil", "Italy", "Thailand", "Kazakhstan", "Ukraine", "Colombia", "Costa Rica", "Vietnam", "Panama", "Australia", "Uzbekistan", "Mozambique", "Guatemala", "Cuba", "Morocco", "Solomon Islands"]}, "2020": {"ranked_players": ["Portugal", "Brazil", "Argentina", "Kazakhstan", "RFU", "Spain", "Iran", "Morocco", "Venezuela", "Paraguay", "Thailand", "Czech Republic", "Vietnam", "Uzbekistan", "Serbia", "Japan", "Guatemala", "Egypt", "Costa Rica", "Angola", "Panama", "Solomon Islands", "Lithuania", "United States"]}}, "handball": {"1976": {"ranked_players": ["Yugoslavia", "Soviet Union", "Poland", "West Germany", "Czechoslovakia", "Japan", "Denmark", "Romania", "Hungary", "United States", "Canada", "Tunisia"]}, "1988": {"ranked_players": ["Soviet Union", "Yugoslavia", "South Korea", "East Germany", "Sweden", "Czechoslovakia", "Hungary", "Spain", "Iceland", "Japan", "Algeria", "United States"]}, "1992": {"ranked_players": ["Unified Team", "Sweden", "France", "Iceland", "Spain", "South Korea", "Hungary", "Czechoslovakia", "Romania", "Germany", "Egypt", "Brazil"]}, "1996": {"ranked_players": ["Croatia", "Sweden", "Spain", "France", "Russia", "Germany", "Egypt", "Switzerland", "United States", "Brazil", "Algeria", "Kuwait"]}, "2000": {"ranked_players": ["Sweden", "Russia", "Germany", "Spain", "France", "FR Yugoslavia", "Egypt", "Slovenia", "South Korea", "Cuba", "Tunisia", "Australia"]}, "2008": {"ranked_players": ["France", "Poland", "Spain", "Iceland", "Croatia", "Denmark", "Russia", "South Korea", "Germany", "Brazil", "Egypt", "China"]}, "2012": {"ranked_players": ["Croatia", "France", "Sweden", "Hungary", "Iceland", "Denmark", "Spain", "Tunisia", "Serbia", "Argentina", "South Korea", "Great Britain"]}, "2016": {"ranked_players": ["Germany", "France", "Denmark", "Poland", "Croatia", "Slovenia", "Brazil", "Qatar", "Egypt", "Sweden", "Argentina", "Tunisia"]}, "2020": {"ranked_players": ["France", "Denmark", "Spain", "Egypt", "Sweden", "Germany", "Norway", "Bahrain", "Japan", "Portugal", "Brazil", "Argentina"]}}, "ice_hockey": {"1924": {"ranked_players": ["Canada", "United States", "Great Britain", "Sweden", "Czechoslovakia", "France", "Belgium", "Switzerland"]}, "1928": {"ranked_players": ["Sweden", "Switzerland", "Great Britain", "Canada", "Belgium", "France", "Czechoslovakia", "Austria", "Germany", "Hungary", "Poland"]}, "1932": {"ranked_players": ["Canada", "United States", "Germany", "Poland"]}, "1948": {"ranked_players": ["Czechoslovakia", "Canada", "Switzerland", "USA", "Sweden", "United Kingdom", "Poland", "Austria", "Italy"]}, "1952": {"ranked_players": ["Canada", "United States", "Sweden", "Czechoslovakia", "Switzerland", "Finland", "Poland", "Germany", "Norway"]}, "1956": {"ranked_players": ["Canada", "Germany", "Soviet Union", "USA", "Czechoslovakia", "Sweden", "Italy", "Austria", "Poland", "Switzerland", "East Germany", "Norway", "Belgium"]}, "1960": {"ranked_players": ["United States", "Canada", "Soviet Union", "Czechoslovakia", "Sweden", "Germany", "Finland", "Japan", "Australia"]}, "1964": {"ranked_players": ["Poland", "Norway", "Japan", "Romania", "Yugoslavia", "Austria", "Italy", "Hungary"]}, "1972": {"ranked_players": ["Soviet Union", "Czechoslovakia", "USA", "Sweden", "Finland", "Poland", "WestGermany", "Norway", "Japan", "Switzerland", "Yugoslavia"]}, "1976": {"ranked_players": ["Soviet Union", "Czechoslovakia", "West Germany", "Finland", "USA", "Poland", "Romania", "Japan", "Switzerland", "Yugoslavia", "Austria", "Bulgaria"]}, "1980": {"ranked_players": ["United States", "Soviet Union", "Sweden", "Finland", "Czechoslovakia", "Canada", "Poland", "Romania", "West Germany", "Netherlands", "Norway", "Japan"]}, "1984": {"ranked_players": ["Soviet Union", "Czechoslovakia", "Sweden", "Canada", "West Germany", "Finland", "Italy", "Yugoslavia", "Poland", "United States", "Austria", "Norway"]}, "1988": {"ranked_players": ["Canada", "West Germany", "Soviet Union", "Finland", "Sweden", "Czechoslovakia", "Switzerland", "USA", "Poland", "Austria", "Norway", "France", "France*"]}, "2002": {"ranked_players": ["Germany", "Belarus", "Sweden", "United States", "Russia", "Czech Republic", "Ukraine", "Finland", "Latvia", "Austria", "Switzerland", "Canada", "France", "Slovakia"]}, "2006": {"ranked_players": ["Finland", "Sweden", "Czech Republic", "Russia", "Slovakia", "Canada", "Switzerland", "United States", "Kazakhstan", "Latvia", "Germany", "Italy"]}, "2010": {"ranked_players": ["United States", "Canada", "Finland", "Slovakia", "Sweden", "Russia", "Czech Republic", "Switzerland", "Belarus", "Norway", "Latvia", "Germany"]}, "2014": {"ranked_players": ["Canada", "Sweden", "United States", "Finland", "Russia", "Slovenia", "Czech Republic", "Latvia", "Switzerland", "Austria", "Norway", "Slovakia"]}, "2018": {"ranked_players": ["Germany", "Russia", "Czech Republic", "Canada", "Finland", "United States", "Norway", "Sweden", "Slovenia", "Switzerland", "Slovakia", "South Korea"]}, "2022": {"ranked_players": ["Slovakia", "Finland", "ROC", "Sweden", "Canada", "Denmark", "Switzerland", "United States", "Czech Republic", "Germany", "Latvia", "China"]}}, "lacrosse": {"1974": {"ranked_players": ["United States", "Canada", "Australia", "England"]}, "1978": {"ranked_players": ["England", "United States", "Canada", "Australia"]}, "1982": {"ranked_players": ["United States", "Australia", "Canada", "England"]}, "1986": {"ranked_players": ["United States", "Canada", "Australia", "England"]}, "1990": {"ranked_players": ["United States", "Canada", "Australia", "England", "Iroquois Nationals"]}, "1994": {"ranked_players": ["United States", "Canada", "Australia", "England", "Iroquois Nationals", "Japan"]}, "1998": {"ranked_players": ["United States", "Canada", "Japan", "Germany", "Scotland", "Sweden", "Australia", "Czech Republic", "Iroquois", "Wales", "England"]}, "2002": {"ranked_players": ["United States", "Canada", "Ireland", "Japan", "Germany", "Scotland", "Australia", "Sweden", "Iroquois", "New Zealand", "Hong Kong", "Wales", "England", "Czech", "South Korea", "Czech Republic", "South", "South Africa"]}, "2006": {"ranked_players": ["Canada", "Iroquois", "Australia", "Finland", "Ireland", "Czech Republic", "Italy", "Germany", "Wales", "Latvia", "Spain", "England", "Netherlands", "Denmark", "Japan", "Scotland", "New Zealand", "South Korea", "Hong Kong", "United States", "Bermuda", "USA"]}, "2010": {"ranked_players": ["United States", "Canada", "Japan", "Australia", "England", "Germany", "Scotland", "Netherlands", "Wales", "Finland", "Spain", "Sweden", "Poland", "New Zealand", "Hong Kong", "Slovakia", "Latvia", "Austria", "Italy", "Bermuda", "Norway", "Denmark", "South Korea", "Argentina", "France", "Mexico", "Iroquois", "Ireland", "Czech Republic", "Switzerland", "Ireland Republic of Ireland", "Switzerland Switzerland", "Czech", "australia"]}, "2014": {"ranked_players": ["United States", "Canada", "Iroquois", "Australia", "Japan", "England", "Scotland", "Israel", "Finland", "Germany", "New Zealand", "Czech", "Netherlands", "Sweden", "Norway", "Italy", "Poland", "Mexico", "Bermuda", "Switzerland", "Wales", "Hong", "Latvia", "Slovakia", "Spain", "Turkey", "France", "Austria", "Russia", "Thailand", "Belgium", "China", "Uganda", "Colombia", "Argentina", "Costa Rica", "Ireland", "South", "Republic", "Korea"]}}, "roller_hockey": {"1999": {"ranked_players": ["Mozambique", "Chile", "Germany", "United States", "Spain", "Portugal", "Argentina", "Italy", "Switzerland", "Brazil", "France", "Angola"]}, "2001": {"ranked_players": ["Argentina", "Portugal", "Italy", "Brazil", "Chile", "France", "Angola", "United States", "Germany", "Netherlands", "Uruguay", "England", "Spain", "Mozambique", "Switzerland"]}, "2003": {"ranked_players": ["Argentina", "Portugal", "Italy", "Spain", "Brazil", "France", "Switzerland", "Angola", "United States", "Chile", "Mozambique", "Germany", "Andorra", "Colombia", "England", "Netherlands"]}, "2005": {"ranked_players": ["Portugal", "Argentina", "Italy", "Spain", "Switzerland", "Angola", "Chile", "Brazil", "Germany", "France", "England", "Andorra", "Netherlands", "Macau", "Mozambique", "United States"]}, "2007": {"ranked_players": ["Portugal", "Argentina", "Spain", "Italy", "Brazil", "France", "Angola", "Switzerland", "Germany", "England", "United States", "Chile", "Mozambique", "Colombia", "Andorra", "Netherlands"]}, "2009": {"ranked_players": ["Argentina", "Spain", "Brazil", "France", "Italy", "Portugal", "Switzerland", "Angola", "Andorra", "Germany", "Chile", "Mozambique", "Colombia", "United States", "England", "Netherlands"]}, "2011": {"ranked_players": ["Portugal", "Spain", "Brazil", "Argentina", "Italy", "Mozambique", "France", "Chile", "Angola", "Germany", "Colombia", "Switzerland", "United States", "England", "South Africa", "Netherlands"]}, "2013": {"ranked_players": ["Spain", "Portugal", "Argentina", "Chile", "Italy", "Brazil", "France", "Mozambique", "Germany", "Angola", "United States", "Switzerland", "South Africa", "Colombia", "Uruguay", "Austria"]}, "2015": {"ranked_players": ["Argentina", "Portugal", "Italy", "Spain", "Angola", "Germany", "Mozambique", "Switzerland", "Colombia", "France", "Chile", "Brazil", "Austria", "Netherlands", "England", "South Africa"]}}, "rugby": {"1987": {"ranked_players": ["New Zealand", "Wales", "Australia", "France", "England", "Ireland", "Scotland", "Fiji", "Canada", "Argentina", "Italy", "Romania", "Zimbabwe", "Tonga", "Japan", "United States"]}, "1991": {"ranked_players": ["Australia", "New Zealand", "England", "Scotland", "France", "Ireland", "Western Samoa", "Canada", "Italy", "Japan", "Wales", "Romania", "Zimbabwe", "Argentina", "Fiji", "United States"]}, "1995": {"ranked_players": ["South Africa", "New Zealand", "England", "France", "Australia", "Western Samoa", "Ireland", "Scotland", "Canada", "Italy", "Wales", "Tonga", "Ivory Coast", "Argentina", "Romania", "Japan"]}, "1999": {"ranked_players": ["Australia", "South Africa", "France", "New Zealand", "Scotland", "England", "Argentina", "Fiji", "Wales", "Samoa", "Ireland", "Uruguay", "Tonga", "Canada", "Romania", "Spain", "Italy", "Japan", "United States", "Namibia"]}, "2003": {"ranked_players": ["England", "New Zealand", "Australia", "France", "South Africa", "Ireland", "Wales", "Scotland", "Argentina", "Samoa", "Fiji", "Italy", "United States", "Romania", "Uruguay", "Canada", "Japan", "Tonga", "Georgia", "Namibia"]}, "2007": {"ranked_players": ["South Africa", "New Zealand", "England", "Wales", "France", "Australia", "Ireland", "Japan"]}, "2011": {"ranked_players": ["South Africa", "New Zealand", "England", "Wales", "Ireland", "Australia", "France", "Japan", "Argentina", "Italy", "Samoa", "Tonga", "Scotland", "Canada", "Fiji", "Georgia", "United States", "Russia", "Namibia", "Romania"]}, "2015": {"ranked_players": ["New Zealand", "South Africa", "England", "Wales", "Australia", "Ireland", "France", "Japan", "Argentina", "Scotland", "Italy", "Georgia", "Fiji", "Tonga", "Samoa", "Romania", "Namibia", "Canada", "United States", "Uruguay"]}, "2019": {"ranked_players": ["South Africa", "New Zealand", "Wales", "Japan", "Australia", "Ireland", "Italy", "Scotland", "Fiji", "Georgia", "Uruguay", "Samoa", "Namibia", "Canada", "Russia", "England", "France"]}}, "soccer": {"1930": {"ranked_players": ["Argentina", "Uruguay", "Yugoslavia", "USA", "Chile", "France", "Mexico", "Brazil", "Romania", "Paraguay", "Peru", "Belgium", "Bolivia"]}, "1934": {"ranked_players": ["Italy", "Germany", "Czechoslovakia", "Austria", "Spain", "Hungary", "Switzerland", "Sweden", "Belgium", "Argentina", "Netherlands", "Egypt", "France", "Romania", "USA", "Brazil"]}, "1950": {"ranked_players": ["Brazil", "Spain", "Sweden", "Uruguay", "Yugoslavia", "Switzerland", "Chile", "USA", "England", "Mexico", "Italy", "Paraguay", "Bolivia"]}, "1954": {"ranked_players": ["Germany FR", "Hungary", "Austria", "Uruguay", "Switzerland", "Brazil", "England", "Yugoslavia", "Turkey", "Italy", "France", "Belgium", "Mexico", "Korea Republic", "Czechoslovakia", "Scotland"]}, "1958": {"ranked_players": ["Brazil", "Sweden", "France", "Germany FR", "Northern Ireland", "Soviet Union", "Wales", "Yugoslavia", "Czechoslovakia", "Hungary", "England", "Paraguay", "Argentina", "Scotland", "Austria", "Mexico"]}, "1962": {"ranked_players": ["Brazil", "Chile", "Czechoslovakia", "Yugoslavia", "Soviet Union", "Hungary", "Germany FR", "England", "Italy", "Argentina", "Uruguay", "Mexico", "Spain", "Colombia", "Bulgaria", "Switzerland"]}, "1966": {"ranked_players": ["England", "Portugal", "Germany FR", "Soviet Union", "Argentina", "Hungary", "Uruguay", "Korea DPR", "Spain", "Brazil", "Italy", "Mexico", "Chile", "France", "Bulgaria", "Switzerland"]}, "1970": {"ranked_players": ["Brazil", "Germany FR", "Italy", "Uruguay", "Soviet Union", "Mexico", "Peru", "England", "Sweden", "Belgium", "Romania", "Israel", "Bulgaria", "Morocco", "Czechoslovakia", "El Salvador"]}, "1974": {"ranked_players": ["Poland", "Germany FR", "Netherlands", "Brazil", "Sweden", "German DR", "Yugoslavia", "Argentina", "Scotland", "Italy", "Bulgaria", "Chile", "Uruguay", "Australia", "Haiti", "Zaire"]}, "1978": {"ranked_players": ["Argentina", "Brazil", "Italy", "Netherlands", "Poland", "Austria", "Peru", "Germany FR", "Scotland", "Tunisia", "Spain", "France", "Sweden", "Hungary", "Mexico", "IR Iran", "Iran"]}, "1982": {"ranked_players": ["Italy", "Germany FR", "Poland", "France", "Brazil", "England", "Soviet Union", "Austria", "Belgium", "Argentina", "Northern Ireland", "Spain", "Algeria", "Hungary", "Scotland", "Yugoslavia", "Cameroon", "Honduras", "Czechoslovakia", "Peru", "Kuwait", "Chile", "New Zealand", "El Salvador"]}, "1986": {"ranked_players": ["Argentina", "France", "Germany FR", "Belgium", "Brazil", "Mexico", "Spain", "England", "Denmark", "Soviet Union", "Italy", "Paraguay", "Morocco", "Poland", "Uruguay", "Bulgaria", "Portugal", "Hungary", "Korea Republic", "Northern Ireland", "Scotland", "Algeria", "Iraq", "Canada"]}, "1990": {"ranked_players": ["Germany FR", "Italy", "Argentina", "England", "Czechoslovakia", "Yugoslavia", "Cameroon", "rn\">Republic of Ireland", "Brazil", "Spain", "Belgium", "Costa Rica", "Romania", "Colombia", "Uruguay", "Netherlands", "Soviet Union", "Scotland", "Austria", "Egypt", "Sweden", "USA", "rn\">United Arab Emirates", "Korea Republic"]}, "1994": {"ranked_players": ["Brazil", "Sweden", "Italy", "Bulgaria", "Germany", "Romania", "Netherlands", "Spain", "Argentina", "Nigeria", "Saudi Arabia", "Belgium", "Switzerland", "Mexico", "USA", "rn\">Republic of Ireland", "Norway", "Russia", "Colombia", "Korea Republic", "Cameroon", "Bolivia", "Morocco", "Greece"]}, "1998": {"ranked_players": ["France", "Brazil", "Croatia", "Netherlands", "Argentina", "Italy", "Germany", "Denmark", "Yugoslavia", "Romania", "England", "Nigeria", "Mexico", "Norway", "Paraguay", "Chile", "Spain", "Morocco", "Jamaica", "Iran", "Colombia", "Belgium", "South Africa", "Austria", "Cameroon", "Korea Republic", "Saudi Arabia", "Scotland", "Tunisia", "Bulgaria", "Japan", "USA"]}, "2002": {"ranked_players": ["Brazil", "Germany", "Korea Republic", "Turkey", "Spain", "Senegal", "England", "USA", "Japan", "Denmark", "Mexico", "rn\">Republic of Ireland", "Belgium", "Sweden", "Paraguay", "Italy", "Costa Rica", "South Africa", "Argentina", "Cameroon", "Portugal", "Russia", "Poland", "Croatia", "Ecuador", "Uruguay", "Tunisia", "Nigeria", "France", "Slovenia", "China PR", "Saudi Arabia"]}, "2006": {"ranked_players": ["Italy", "Germany", "Portugal", "France", "Brazil", "Argentina", "England", "Ukraine", "Spain", "Switzerland", "Netherlands", "Ecuador", "Ghana", "Sweden", "Australia", "Mexico", "Korea Republic", "C\u00ef\u00bf\u00bdte d'Ivoire", "Czech Republic", "Paraguay", "Poland", "Croatia", "Angola", "Tunisia", "Saudi Arabia", "Japan", "USA", "rn\">Trinidad and Tobago", "Costa Rica", "rn\">Serbia and Montenegro", "Togo", "Iran", "IR Iran"]}, "2010": {"ranked_players": ["Netherlands", "Spain", "Germany", "Uruguay", "Argentina", "Brazil", "Paraguay", "Ghana", "Japan", "Chile", "Portugal", "USA", "England", "Korea Republic", "Slovakia", "Mexico", "C\u00ef\u00bf\u00bdte d'Ivoire", "Australia", "Slovenia", "South Africa", "Switzerland", "Denmark", "Serbia", "Greece", "New Zealand", "Italy", "Nigeria", "France", "Honduras", "Algeria", "Cameroon", "Korea DPR"]}, "2014": {"ranked_players": ["Germany", "Netherlands", "Argentina", "Brazil", "Colombia", "Belgium", "France", "Costa Rica", "Chile", "Mexico", "Switzerland", "Uruguay", "Greece", "Algeria", "USA", "Nigeria", "Portugal", "Ecuador", "Croatia", "rn\">Bosnia and Herzegovina", "C\u00ef\u00bf\u00bdte d'Ivoire", "Spain", "Italy", "Russia", "Ghana", "Korea Republic", "Japan", "England", "IR Iran", "Australia", "Honduras", "Cameroon"]}}, "volleyball": {"1965": {"ranked_players": ["Soviet Union", "Poland", "Czechoslovakia", "East Germany", "Hungary", "Yugoslavia", "Japan", "Romania", "Bulgaria", "Netherlands", "France"]}, "1969": {"ranked_players": ["East Germany", "Japan", "Czechoslovakia", "Brazil", "Romania", "Soviet Union", "Poland", "Bulgaria", "Cuba", "West Germany", "Tunisia"]}, "1977": {"ranked_players": ["Soviet Union", "Poland", "Cuba", "Japan", "China", "Brazil", "Bulgaria", "South Korea", "Mexico", "United States", "Egypt", "Canada"]}, "1981": {"ranked_players": ["Soviet Union", "Cuba", "Brazil", "Poland", "China", "Japan", "Italy", "Tunisia"]}, "1985": {"ranked_players": ["United States", "Czechoslovakia", "Soviet Union", "Brazil", "Argentina", "Japan", "South Korea", "Egypt"]}, "1989": {"ranked_players": ["Cuba", "Italy", "Soviet Union", "Brazil", "United States", "South Korea", "Japan", "Cameroon"]}, "1991": {"ranked_players": ["Soviet Union", "United States", "Cuba", "Germany", "Japan", "Tunisia", "Brazil", "South Korea", "Algeria", "Mexico", "Iran", "Chile"]}, "1995": {"ranked_players": ["Italy", "Netherlands", "Brazil", "United States", "Japan", "Cuba", "Argentina", "China", "Canada", "South Korea", "Egypt", "Tunisia"]}, "1999": {"ranked_players": ["Russia", "Cuba", "United States", "Italy", "Spain", "Brazil", "South Korea", "Canada", "Argentina", "Japan", "China", "Tunisia"]}, "2003": {"ranked_players": ["United States", "Brazil", "Serbia and Montenegro", "Italy", "France", "South Korea", "Canada", "Japan", "China", "Tunisia", "Venezuela", "Egypt"]}, "2007": {"ranked_players": ["Brazil", "Russia", "Bulgaria", "United States", "Spain", "Australia", "Argentina", "Puerto Rico", "Japan", "Egypt", "South Korea", "Tunisia"]}, "2011": {"ranked_players": ["Russia", "Poland", "Cuba", "Brazil", "Italy", "Argentina", "Iran", "Serbia", "United States", "Japan", "Egypt", "China"]}, "2015": {"ranked_players": ["Italy", "United States", "Poland", "Russia", "Argentina", "Japan", "Canada", "Australia", "Iran", "Egypt", "Venezuela", "Tunisia"]}, "2019": {"ranked_players": ["Brazil", "Poland", "United States", "Japan", "Argentina", "Italy", "Russia", "Iran", "Canada", "Egypt", "Australia", "Tunisia"]}}, "water_polo": {"1979": {"ranked_players": ["Hungary", "United States", "Yugoslavia", "Soviet Union", "West Germany", "Italy", "Romania", "Bulgaria"]}, "1981": {"ranked_players": ["Soviet Union", "Yugoslavia", "Cuba", "United States", "Hungary", "Spain", "Australia", "Bulgaria"]}, "1983": {"ranked_players": ["Soviet Union", "West Germany", "Italy", "United States", "Cuba", "Spain", "Hungary", "Netherlands"]}, "1985": {"ranked_players": ["United States", "Italy", "Netherlands", "Greece", "West Germany", "Yugoslavia", "Australia", "Spain"]}, "1993": {"ranked_players": ["Hungary", "Italy", "Australia", "Greece", "United States", "Cuba", "Germany", "Russia"]}, "1995": {"ranked_players": ["Hungary", "Russia", "Spain", "United States", "Italy", "Greece", "Croatia", "Netherlands"]}, "1999": {"ranked_players": ["FR Yugoslavia", "Hungary", "Italy", "Spain", "United States", "Russia", "Greece", "Australia"]}, "2002": {"ranked_players": ["FR Yugoslavia", "Hungary", "Italy", "Spain", "United States", "Russia", "Greece", "Australia"]}, "2010": {"ranked_players": ["Romania", "Australia", "China", "Iran", "Croatia", "Spain", "Serbia", "United States"]}, "2014": {"ranked_players": ["Australia", "Montenegro", "Kazakhstan", "South Africa", "Serbia", "Hungary", "United States", "Croatia"]}, "2018": {"ranked_players": ["Croatia", "United States", "Japan", "South Africa", "Hungary", "Australia", "Serbia", "Germany"]}}}